fitsmap/__init__.py
fitsmap/__main__.py
fitsmap/_version.py
fitsmap/cartographer.py
fitsmap/convert.py
fitsmap/kdbush.py
fitsmap/output_manager.py
fitsmap/padded_array.py
fitsmap/supercluster.py
fitsmap/utils.py
fitsmap/support/LabelControl.css
fitsmap/support/LabelControl.min.css
fitsmap/support/MarkerCluster.Default.css
fitsmap/support/MarkerCluster.Default.min.css
fitsmap/support/MarkerCluster.css
fitsmap/support/MarkerCluster.min.css
fitsmap/support/MarkerPopup.css
fitsmap/support/MarkerPopup.min.css
fitsmap/support/SettingsControl.css
fitsmap/support/SettingsControl.min.css
fitsmap/support/TileNearestNeighbor.css
fitsmap/support/TileNearestNeighbor.min.css
fitsmap/support/customSearch.js
fitsmap/support/customSearch.min.js
fitsmap/support/favicon.ico
fitsmap/support/fitsmapScale.js
fitsmap/support/fitsmapScale.min.js
fitsmap/support/l.ellipse.js
fitsmap/support/l.ellipse.min.js
fitsmap/support/labelControl.js
fitsmap/support/labelControl.min.js
fitsmap/support/loading-logo.svg
fitsmap/support/settingsControl.js
fitsmap/support/settingsControl.min.js
fitsmap/support/tiledMarkers.js
fitsmap/support/tiledMarkers.min.js
fitsmap/support/urlCoords.js.tmp
fitsmap/support/vector-tile.js
fitsmap/support/vector-tile.min.js
fitsmap-0.11.2.dist-info/licenses/LICENSE
fitsmap-0.11.2.dist-info/METADATA
fitsmap-0.11.2.dist-info/WHEEL
fitsmap-0.11.2.dist-info/entry_points.txt
fitsmap-0.11.2.dist-info/top_level.txt
fitsmap-0.11.2.dist-info/RECORD
