Metadata-Version: 2.4
Name: fitsmap
Version: 0.11.2
Summary: A Simple, Lightweight Tool For Displaying Interactive Astronomical Image and Catalog Data
Author-email: Ryan Hausen <rhausen@jhu.edu>, Brant Robertson <brant@ucsc.edu>
License-Expression: MIT
Classifier: Development Status :: 4 - Beta
Classifier: Intended Audience :: Science/Research
Classifier: Programming Language :: Python :: 3
Classifier: Programming Language :: Python :: 3.9
Classifier: Programming Language :: Python :: 3.10
Classifier: Programming Language :: Python :: 3.11
Classifier: Programming Language :: Python :: 3.12
Classifier: Programming Language :: Python :: 3.13
Classifier: Topic :: Scientific/Engineering :: Astronomy
Classifier: Topic :: Scientific/Engineering :: Visualization
Classifier: Operating System :: OS Independent
Requires-Python: >=3.9
License-File: LICENSE
Requires-Dist: astropy>=6.0.1
Requires-Dist: cbor2>=5.7.0
Requires-Dist: click>=8.1.8
Requires-Dist: mapbox_vector_tile>=2.2.0
Requires-Dist: matplotlib>=3.9.4
Requires-Dist: numpy>=1.26.4
Requires-Dist: pillow>=11.3.0
Requires-Dist: protobuf>=6.32.0
Requires-Dist: ray>=2.49.0
Requires-Dist: shapely>=2.0.7
Requires-Dist: scikit-image>=0.24.0
Requires-Dist: tqdm>=4.67.1
Dynamic: license-file
